Workbook

Sheet README
A1: GSCMTF INPUT TRACKER v2 — USER GUIDE
A2: Global Supply Chain Management Task Force | US-OCHA Funded Global Project | FAO / CSLO
A4: PURPOSE
B5: Manual input tracker for the GSCMTF dashboard. Data entered here feeds the HTML Control Tower and GSCMTF performance reports. Budget and order counts are auto-aggregated via SUMIF/COUNTIF formulas.
A7: HOW TO USE
A8: Step 1 | B8: Go to your Country Sheet tab (e.g. 'Bangladesh', 'Chad'…)
A9: Step 2 | B9: Fill in all YELLOW cells with input data (blue text = manual input).
A10: Step 3 | B10: Do NOT edit cells with black text on a light-blue background — these are formula cells.
A11: Step 4 | B11: Enter budget lines in SECTION 8 (Budget Detail) — Budget Spent & Committed in Section 1 update automatically.
A12: Step 5 | B12: Enter each order in SECTION 9 (Orders Detail) — the order pipeline counts in Section 3 update automatically.
A13: Step 6 | B13: Update 'Last Updated' date and 'Updated by' fields at the top of your sheet.
A14: Step 7 | B14: GLOBAL_SUMMARY reflects all country inputs automatically via formulas.
A16: SHEET STRUCTURE
A17: README (this sheet) | B17: User guide and instructions.
A18: GLOBAL_SUMMARY | B18: Auto-aggregated view. Do not edit directly.
A19: Bangladesh → Syria | B19: One input sheet per country (9 sheets).
A21: SECTIONS PER COUNTRY
A22: Section 1 | B22: Programmatic: Budget, Beneficiaries, Distribution timeline, Project details. Budget Spent & Committed are auto-calculated from Section 8.
A23: Section 2 | B23: Commodities / Items: List of food/NFI items being distributed.
A24: Section 3 | B24: SC Orders: Pipeline stage counts (Pending → Delivered). Auto-counted from Section 9.
A25: Section 4 | B25: SC Inventory: Stock on hand, in transit, warehouse capacity and locations.
A26: Section 5 | B26: SC Deliveries & Last Mile: Delivery tracking and partner information.
A27: Section 6 | B27: SC KPIs: On-Time Delivery rate, Stockout Risk, overall SC assessment.
A28: Section 7 | B28: Risk Register: Up to 8 active SC risks with level, description, mitigation and owner.
A29: Section 8 | B29: ▶ BUDGET DETAIL TABLE: One row per budget expenditure or commitment. Enter category, description, vendor, amount, date and payment status. Budget Spent (= rows with status 'Spent') and Budget Committed (= rows with status 'Committed') auto-aggregate into Section 1.
A30: Section 9 | B30: ▶ ORDERS DETAIL TABLE: One row per order/PO. Enter commodity, quantities, dates and status. The pipeline counts in Section 3 (Pending / Confirmed / In Production / Shipped / Delivered) auto-count based on the status column.
A32: COLOUR CODING
A33: Yellow bg / Blue text | B33: Manual input cell — enter your data here.
A34: Blue-tint bg / Black text | B34: Formula cell — auto-calculated, do not edit.
A35: ⚡ symbol in notes | B35: Cell is fed by a SUMIF or COUNTIF from a detail table below.
A37: UPDATE FREQUENCY | B37: Update before each GSCMTF meeting (bi-weekly). CSLO Secretariat will validate prior to each Task Force session.
A38: CONTACT | B38: cslo-support@fao.org
A39: VERSION | B39: v2.0 | April 2026 | GSCMTF / CSLO

Sheet GLOBAL_SUMMARY
A1: GSCMTF | US-OCHA Global Project — GLOBAL SUMMARY DASHBOARD
A2: Auto-aggregated from all 9 country input sheets | FAO / CSLO
A4: Country | B4: Status | C4: Total Budget (USD) | D4: Spent (USD) | E4: Budget Util % | F4: Target Beneficiaries | G4: Reached Benef. | H4: Benef. Coverage % | I4: Distrib. Progress % | J4: Total Orders | K4: On Hand (MT) | L4: In Transit (MT) | M4: On-Time Delivery % | N4: Stockout Risk
A5: Bangladesh | B5: =Bangladesh!B6 -> On Track | C5: =Bangladesh!B7 -> 4500000 | D5: =Bangladesh!B8 -> 1602000 | E5: =Bangladesh!B11 -> 0.356 | F5: =Bangladesh!B12 -> 125000 | G5: =Bangladesh!B13 -> 58000 | H5: =Bangladesh!B14 -> 0.464 | I5: =Bangladesh!B17 -> 0.41666667 | J5: =Bangladesh!B40 -> 12 | K5: =Bangladesh!B44 -> 620 | L5: =Bangladesh!B45 -> 180 | M5: =Bangladesh!B69 -> 0.75 | N5: =Bangladesh!B70 -> Low
A6: Chad | B6: =Chad!B6 -> At Risk | C6: =Chad!B7 -> 6200000 | D6: =Chad!B8 -> 1850000 | E6: =Chad!B11 -> 0.2983871 | F6: =Chad!B12 -> 210000 | G6: =Chad!B13 -> 52000 | H6: =Chad!B14 -> 0.24761905 | I6: =Chad!B17 -> 0.21428571 | J6: =Chad!B40 -> 8 | K6: =Chad!B44 -> 310 | L6: =Chad!B45 -> 90 | M6: =Chad!B69 -> 0.44 | N6: =Chad!B70 -> High
A7: Colombia | B7: =Colombia!B6 -> 0 | C7: =Colombia!B7 -> 0 | D7: =Colombia!B8 -> 0 | E7: =Colombia!B11 | F7: =Colombia!B12 -> 0 | G7: =Colombia!B13 -> 0 | H7: =Colombia!B14 | I7: =Colombia!B17 | J7: =Colombia!B40 -> 0 | K7: =Colombia!B44 -> 0 | L7: =Colombia!B45 -> 0 | M7: =Colombia!B69 -> 0 | N7: =Colombia!B70 -> 0
A8: DRC | B8: =DRC!B6 -> 0 | C8: =DRC!B7 -> 0 | D8: =DRC!B8 -> 0 | E8: =DRC!B11 | F8: =DRC!B12 -> 0 | G8: =DRC!B13 -> 0 | H8: =DRC!B14 | I8: =DRC!B17 | J8: =DRC!B40 -> 0 | K8: =DRC!B44 -> 0 | L8: =DRC!B45 -> 0 | M8: =DRC!B69 -> 0 | N8: =DRC!B70 -> 0
A9: Ethiopia | B9: =Ethiopia!B6 -> 0 | C9: =Ethiopia!B7 -> 0 | D9: =Ethiopia!B8 -> 0 | E9: =Ethiopia!B11 | F9: =Ethiopia!B12 -> 0 | G9: =Ethiopia!B13 -> 0 | H9: =Ethiopia!B14 | I9: =Ethiopia!B17 | J9: =Ethiopia!B40 -> 0 | K9: =Ethiopia!B44 -> 0 | L9: =Ethiopia!B45 -> 0 | M9: =Ethiopia!B69 -> 0 | N9: =Ethiopia!B70 -> 0
A10: Haiti | B10: =Haiti!B6 -> 0 | C10: =Haiti!B7 -> 0 | D10: =Haiti!B8 -> 0 | E10: =Haiti!B11 | F10: =Haiti!B12 -> 0 | G10: =Haiti!B13 -> 0 | H10: =Haiti!B14 | I10: =Haiti!B17 | J10: =Haiti!B40 -> 0 | K10: =Haiti!B44 -> 0 | L10: =Haiti!B45 -> 0 | M10: =Haiti!B69 -> 0 | N10: =Haiti!B70 -> 0
A11: Honduras | B11: =Honduras!B6 -> 0 | C11: =Honduras!B7 -> 0 | D11: =Honduras!B8 -> 0 | E11: =Honduras!B11 | F11: =Honduras!B12 -> 0 | G11: =Honduras!B13 -> 0 | H11: =Honduras!B14 | I11: =Honduras!B17 | J11: =Honduras!B40 -> 0 | K11: =Honduras!B44 -> 0 | L11: =Honduras!B45 -> 0 | M11: =Honduras!B69 -> 0 | N11: =Honduras!B70 -> 0
A12: Myanmar | B12: =Myanmar!B6 -> 0 | C12: =Myanmar!B7 -> 0 | D12: =Myanmar!B8 -> 0 | E12: =Myanmar!B11 | F12: =Myanmar!B12 -> 0 | G12: =Myanmar!B13 -> 0 | H12: =Myanmar!B14 | I12: =Myanmar!B17 | J12: =Myanmar!B40 -> 0 | K12: =Myanmar!B44 -> 0 | L12: =Myanmar!B45 -> 0 | M12: =Myanmar!B69 -> 0 | N12: =Myanmar!B70 -> 0
A13: Syria | B13: =Syria!B6 -> 0 | C13: =Syria!B7 -> 0 | D13: =Syria!B8 -> 0 | E13: =Syria!B11 | F13: =Syria!B12 -> 0 | G13: =Syria!B13 -> 0 | H13: =Syria!B14 | I13: =Syria!B17 | J13: =Syria!B40 -> 0 | K13: =Syria!B44 -> 0 | L13: =Syria!B45 -> 0 | M13: =Syria!B69 -> 0 | N13: =Syria!B70 -> 0
A14: TOTAL / AVERAGE | C14: =SUM(C5:C13) -> 10700000 | D14: =SUM(D5:D13) -> 3452000 | E14: =IFERROR(D14/C14,"") -> 0.32261682 | F14: =SUM(F5:F13) -> 335000 | G14: =SUM(G5:G13) -> 110000 | H14: =IFERROR(G14/F14,"") -> 0.32835821 | J14: =SUM(J5:J13) -> 20 | K14: =SUM(K5:K13) -> 930 | L14: =SUM(L5:L13) -> 270 | M14: =IFERROR(AVERAGE(M5:M13),"") -> 0.13222222
A16: GSCMTF | FAO–CSLO | Data sourced from country sheets | Confidential
A17: All figures auto-pulled from individual country sheets. Budget Spent & Committed are SUMIF aggregates from each country's Budget Detail table. Order counts are COUNTIF aggregates from each country's Orders Detail table. Update data in country sheets — this summary refreshes automatically.

Sheet Bangladesh
A1: GSCMTF | US-OCHA Global Project — Bangladesh (BGD) | Region: Asia
A2: FAO Supply Chain Orchestration Unit (CSLO) | Confidential — Internal Use Only
A3: Last Updated: | C3: Updated by:
A5: ▌ SECTION 1 — PROGRAMMATIC INFORMATION
A6: Project Status | B6: On Track | D6: Select current overall project status
A7: Total Budget (USD) | B7: 4500000 | C7: USD | D7: Total budget allocated to this country
A8: Budget Spent to Date (auto) | B8: =IFERROR(SUMIF(H91:H125,"Spent",F91:F125),0) -> 1602000 | C8: USD | D8: ⚡ Auto-sum from Budget Detail table (Section 8)
A9: Budget Committed (auto) | B9: =IFERROR(SUMIF(H91:H125,"Committed",F91:F125),0) -> 415000 | C9: USD | D9: ⚡ Auto-sum from Budget Detail table (Section 8)
A10: Budget Available (auto) | B10: =IFERROR(B7-B8-B9,"") -> 2483000 | C10: USD | D10: Auto-calculated: Total − Spent − Committed
A11: Budget Utilized % (auto) | B11: =IFERROR(B8/B7,"") -> 0.356 | C11: % | D11: Auto-calculated
A12: Target Beneficiaries | B12: 125000 | C12: # | D12: Total number of targeted beneficiaries
A13: Beneficiaries Reached | B13: 58000 | C13: # | D13: Cumulative beneficiaries reached to date
A14: Beneficiary Coverage % (auto) | B14: =IFERROR(B13/B12,"") -> 0.464 | C14: % | D14: Auto-calculated
A15: Total Distribution Months | B15: 12 | C15: months | D15: Total planned distribution months
A16: Distributions Completed | B16: 5 | C16: months | D16: Number of distribution months completed
A17: Distribution Progress % (auto) | B17: =IFERROR(B16/B15,"") -> 0.41666667 | C17: % | D17: Auto-calculated
A18: Next Distribution Date | B18: 46127 | C18: date | D18: Planned date of next distribution
A19: Project Start Date | B19: 45689 | C19: date | D19: Official project start date
A20: Project End Date | B20: 46081 | C20: date | D20: Official project end date
A21: Project Officer (FAO) | B21: M. Rahman | D21: Name of responsible FAO Project Officer
A22: FAO Country Office | B22: FAO Bangladesh (Dhaka) | D22: FAO country office responsible for implementation
A24: ▌ SECTION 2 — COMMODITIES / ITEMS DISTRIBUTED
A25: Commodity / Item 1 | B25: Rice | C25: name | D25: e.g. Rice, Lentils, Cooking Oil, CSB+, Soap, NFIs…
A26: Commodity / Item 2 | B26: Lentils | C26: name | D26: e.g. Rice, Lentils, Cooking Oil, CSB+, Soap, NFIs…
A27: Commodity / Item 3 | B27: Cooking Oil | C27: name | D27: e.g. Rice, Lentils, Cooking Oil, CSB+, Soap, NFIs…
A28: Commodity / Item 4 | B28: Salt | C28: name | D28: e.g. Rice, Lentils, Cooking Oil, CSB+, Soap, NFIs…
A29: Commodity / Item 5 | B29: CSB+ | C29: name | D29: e.g. Rice, Lentils, Cooking Oil, CSB+, Soap, NFIs…
A30: Commodity / Item 6 | C30: name | D30: e.g. Rice, Lentils, Cooking Oil, CSB+, Soap, NFIs…
A31: Commodity / Item 7 | C31: name | D31: e.g. Rice, Lentils, Cooking Oil, CSB+, Soap, NFIs…
A32: Commodity / Item 8 | C32: name | D32: e.g. Rice, Lentils, Cooking Oil, CSB+, Soap, NFIs…
A34: ▌ SECTION 3 — SUPPLY CHAIN: ORDERS (auto-counted from Section 9 detail table)
A35: Orders — Pending (auto) | B35: =IFERROR(COUNTIF(M129:M178,"Pending"),0) -> 2 | C35: # | D35: ⚡ Auto-count from Orders Detail table (Section 9)
A36: Orders — Confirmed (auto) | B36: =IFERROR(COUNTIF(M129:M178,"Confirmed"),0) -> 2 | C36: # | D36: ⚡ Auto-count from Orders Detail table (Section 9)
A37: Orders — In Production (auto) | B37: =IFERROR(COUNTIF(M129:M178,"In Production"),0) -> 0 | C37: # | D37: ⚡ Auto-count from Orders Detail table (Section 9)
A38: Orders — Shipped (auto) | B38: =IFERROR(COUNTIF(M129:M178,"Shipped"),0) -> 2 | C38: # | D38: ⚡ Auto-count from Orders Detail table (Section 9)
A39: Orders — Delivered (auto) | B39: =IFERROR(COUNTIF(M129:M178,"Delivered"),0) -> 6 | C39: # | D39: ⚡ Auto-count from Orders Detail table (Section 9)
A40: Total Orders (auto) | B40: =IFERROR(SUM(B35:B39),0) -> 12 | C40: # | D40: Auto-calculated: sum of all pipeline stages
A41: Order Fulfillment Rate | B41: 0.82 | C41: % | D41: Manual KPI: % of expected orders fulfilled to date
A43: ▌ SECTION 4 — SUPPLY CHAIN: INVENTORY
A44: Stock On Hand | B44: 620 | C44: MT | D44: Physical stock in FAO warehouses
A45: Stock In Transit | B45: 180 | C45: MT | D45: Stock en route to destination warehouses
A46: Total Stock (auto) | B46: =IFERROR(B44+B45,"") -> 800 | C46: MT | D46: Auto-calculated
A47: Warehouse Capacity (total) | B47: 1400 | C47: MT | D47: Total warehouse capacity available
A48: Capacity Utilization % (auto) | B48: =IFERROR((B44+B45)/B47,"") -> 0.57142857 | C48: % | D48: Auto-calculated
A49: Warehouse Location 1 | B49: Dhaka | C49: city | D49: Main hub
A50: Warehouse Location 2 | B50: Cox's Bazar | C50: city | D50: Secondary hub (if applicable)
A51: Warehouse Location 3 | B51: Chittagong | C51: city
A52: Warehouse Location 4 | C52: city
A54: ▌ SECTION 5 — SUPPLY CHAIN: DELIVERIES & LAST MILE
A55: Planned Deliveries (total) | B55: 12 | C55: # | D55: Total delivery events planned
A56: Dispatched | B56: 7 | C56: # | D56: Delivery events dispatched from warehouse
A57: Received by Partners | B57: 6 | C57: # | D57: Confirmed received by implementing partners
A58: Last Mile Completed | B58: 5 | C58: # | D58: Completed to final beneficiaries
A59: Dispatch Rate % (auto) | B59: =IFERROR(B56/B55,"") -> 0.58333333 | C59: % | D59: Auto-calculated
A60: Partner Receipt Rate % (auto) | B60: =IFERROR(B57/B55,"") -> 0.5 | C60: % | D60: Auto-calculated
A61: Last Mile Rate % (auto) | B61: =IFERROR(B58/B55,"") -> 0.41666667 | C61: % | D61: Auto-calculated
A62: Main Transport Mode | B62: Road + Sea | D62: e.g. Road, River, Air, Sea, Mixed
A63: Last Mile Partner 1 | B63: WFP
A64: Last Mile Partner 2 | B64: BRAC
A65: Last Mile Partner 3 | B65: UNHCR
A66: Last Mile Partner 4
A68: ▌ SECTION 6 — SC PERFORMANCE KPIs
A69: On-Time Delivery Rate | B69: 0.75 | C69: % | D69: % of deliveries on time vs. planned schedule
A70: Stockout Risk Level | B70: Low | D70: Select stockout risk assessment
A71: SC Overall Assessment | D71: Traffic-light assessment of overall SC health
A72: SC Comments / Notes | D72: Key issues, highlights, actions needed
A74: ▌ SECTION 7 — RISK REGISTER
A75: Risk # | B75: Risk Level | C75: Risk Description | D75: Mitigation Measure / Owner
A76: 1 | B76: Medium | C76: Monsoon season logistics disruption (Jun-Sep) | D76: Pre-positioning stocks before onset — Logistics Officer
A77: 2 | B77: Low | C77: Supplier lead time variance | D77: Buffer stock at 30% — Procurement Officer
A78: 3
A79: 4
A80: 5
A81: 6
A82: 7
A83: 8
A85: GSCMTF | FAO — CSLO | Confidential — For Internal Use Only
A86: 🔵 Blue text = Manual input | ⚫ Black text = Auto-calculated formula | ⚡ = Fed by detail table below | Yellow bg = Input cell | Blue-tint bg = Formula cell
A89: ▌ SECTION 8 — BUDGET DETAIL | Enter each budget line here → feeds Section 1 (Budget Spent & Committed)
A90: # | B90: Budget Category | C90: Description / Activity | D90: Vendor / Supplier / Partner | E90: Reference / Contract # | F90: Amount (USD) | G90: Date | H90: Payment Status | I90: Notes / Remarks
A91: 1 | B91: Food Procurement | C91: Rice - Round 1 | D91: ABC Agri | E91: PO-001 | F91: 850000 | G91: 45703 | H91: Spent
A92: 2 | B92: Food Procurement | C92: Lentils + Oil | D92: XYZ Foods | E92: PO-002 | F92: 420000 | G92: 45726 | H92: Spent
A93: 3 | B93: Logistics & Transport | C93: Shipping Chittagong | D93: FastLog | E93: INV-010 | F93: 180000 | G93: 45736 | H93: Spent
A94: 4 | B94: Warehousing | C94: Warehouse rental Q1 | D94: StoreCo | E94: INV-020 | F94: 45000 | G94: 45748 | H94: Spent
A95: 5 | B95: Food Procurement | C95: CSB+ supply | D95: NutriCorp | E95: PO-003 | F95: 320000 | G95: 45778 | H95: Committed
A96: 6 | B96: Logistics & Transport | C96: Last mile transport | D96: RoadTrans | E96: INV-030 | F96: 95000 | G96: 45792 | H96: Committed
A97: 7 | B97: HR & Staffing | C97: SC Coordinator salary Q1 | D97: FAO | E97: HR-001 | F97: 85000 | G97: 45748 | H97: Spent
A98: 8 | B98: Admin & Overheads | C98: Office + comms | D98: FAO | E98: ADM-001 | F98: 22000 | G98: 45748 | H98: Spent
A99: 9
A100: 10
A101: 11
A102: 12
A103: 13
A104: 14
A105: 15
A106: 16
A107: 17
A108: 18
A109: 19
A110: 20
...

Sheet Chad
A1: GSCMTF | US-OCHA Global Project — Chad (TCD) | Region: West Africa
A2: FAO Supply Chain Orchestration Unit (CSLO) | Confidential — Internal Use Only
A3: Last Updated: | C3: Updated by:
A5: ▌ SECTION 1 — PROGRAMMATIC INFORMATION
A6: Project Status | B6: At Risk | D6: Select current overall project status
A7: Total Budget (USD) | B7: 6200000 | C7: USD | D7: Total budget allocated to this country
A8: Budget Spent to Date (auto) | B8: =IFERROR(SUMIF(H91:H125,"Spent",F91:F125),0) -> 1850000 | C8: USD | D8: ⚡ Auto-sum from Budget Detail table (Section 8)
A9: Budget Committed (auto) | B9: =IFERROR(SUMIF(H91:H125,"Committed",F91:F125),0) -> 560000 | C9: USD | D9: ⚡ Auto-sum from Budget Detail table (Section 8)
A10: Budget Available (auto) | B10: =IFERROR(B7-B8-B9,"") -> 3790000 | C10: USD | D10: Auto-calculated: Total − Spent − Committed
A11: Budget Utilized % (auto) | B11: =IFERROR(B8/B7,"") -> 0.2983871 | C11: % | D11: Auto-calculated
A12: Target Beneficiaries | B12: 210000 | C12: # | D12: Total number of targeted beneficiaries
A13: Beneficiaries Reached | B13: 52000 | C13: # | D13: Cumulative beneficiaries reached to date
A14: Beneficiary Coverage % (auto) | B14: =IFERROR(B13/B12,"") -> 0.24761905 | C14: % | D14: Auto-calculated
A15: Total Distribution Months | B15: 14 | C15: months | D15: Total planned distribution months
A16: Distributions Completed | B16: 3 | C16: months | D16: Number of distribution months completed
A17: Distribution Progress % (auto) | B17: =IFERROR(B16/B15,"") -> 0.21428571 | C17: % | D17: Auto-calculated
A18: Next Distribution Date | B18: 46122 | C18: date | D18: Planned date of next distribution
A19: Project Start Date | B19: 45658 | C19: date | D19: Official project start date
A20: Project End Date | B20: 46112 | C20: date | D20: Official project end date
A21: Project Officer (FAO) | B21: A. Mahamat | D21: Name of responsible FAO Project Officer
A22: FAO Country Office | B22: FAO Chad (N'Djamena) | D22: FAO country office responsible for implementation
A24: ▌ SECTION 2 — COMMODITIES / ITEMS DISTRIBUTED
A25: Commodity / Item 1 | B25: Sorghum | C25: name | D25: e.g. Rice, Lentils, Cooking Oil, CSB+, Soap, NFIs…
A26: Commodity / Item 2 | B26: Cowpeas | C26: name | D26: e.g. Rice, Lentils, Cooking Oil, CSB+, Soap, NFIs…
A27: Commodity / Item 3 | B27: CSB+ | C27: name | D27: e.g. Rice, Lentils, Cooking Oil, CSB+, Soap, NFIs…
A28: Commodity / Item 4 | B28: Vegetable Oil | C28: name | D28: e.g. Rice, Lentils, Cooking Oil, CSB+, Soap, NFIs…
A29: Commodity / Item 5 | B29: Salt | C29: name | D29: e.g. Rice, Lentils, Cooking Oil, CSB+, Soap, NFIs…
A30: Commodity / Item 6 | C30: name | D30: e.g. Rice, Lentils, Cooking Oil, CSB+, Soap, NFIs…
A31: Commodity / Item 7 | C31: name | D31: e.g. Rice, Lentils, Cooking Oil, CSB+, Soap, NFIs…
A32: Commodity / Item 8 | C32: name | D32: e.g. Rice, Lentils, Cooking Oil, CSB+, Soap, NFIs…
A34: ▌ SECTION 3 — SUPPLY CHAIN: ORDERS (auto-counted from Section 9 detail table)
A35: Orders — Pending (auto) | B35: =IFERROR(COUNTIF(M129:M178,"Pending"),0) -> 3 | C35: # | D35: ⚡ Auto-count from Orders Detail table (Section 9)
A36: Orders — Confirmed (auto) | B36: =IFERROR(COUNTIF(M129:M178,"Confirmed"),0) -> 2 | C36: # | D36: ⚡ Auto-count from Orders Detail table (Section 9)
A37: Orders — In Production (auto) | B37: =IFERROR(COUNTIF(M129:M178,"In Production"),0) -> 0 | C37: # | D37: ⚡ Auto-count from Orders Detail table (Section 9)
A38: Orders — Shipped (auto) | B38: =IFERROR(COUNTIF(M129:M178,"Shipped"),0) -> 0 | C38: # | D38: ⚡ Auto-count from Orders Detail table (Section 9)
A39: Orders — Delivered (auto) | B39: =IFERROR(COUNTIF(M129:M178,"Delivered"),0) -> 3 | C39: # | D39: ⚡ Auto-count from Orders Detail table (Section 9)
A40: Total Orders (auto) | B40: =IFERROR(SUM(B35:B39),0) -> 8 | C40: # | D40: Auto-calculated: sum of all pipeline stages
A41: Order Fulfillment Rate | B41: 0.52 | C41: % | D41: Manual KPI: % of expected orders fulfilled to date
A43: ▌ SECTION 4 — SUPPLY CHAIN: INVENTORY
A44: Stock On Hand | B44: 310 | C44: MT | D44: Physical stock in FAO warehouses
A45: Stock In Transit | B45: 90 | C45: MT | D45: Stock en route to destination warehouses
A46: Total Stock (auto) | B46: =IFERROR(B44+B45,"") -> 400 | C46: MT | D46: Auto-calculated
A47: Warehouse Capacity (total) | B47: 900 | C47: MT | D47: Total warehouse capacity available
A48: Capacity Utilization % (auto) | B48: =IFERROR((B44+B45)/B47,"") -> 0.44444444 | C48: % | D48: Auto-calculated
A49: Warehouse Location 1 | B49: N'Djamena | C49: city | D49: Main hub
A50: Warehouse Location 2 | B50: Moundou | C50: city | D50: Secondary hub (if applicable)
A51: Warehouse Location 3 | B51: Abéché | C51: city
A52: Warehouse Location 4 | C52: city
A54: ▌ SECTION 5 — SUPPLY CHAIN: DELIVERIES & LAST MILE
A55: Planned Deliveries (total) | B55: 14 | C55: # | D55: Total delivery events planned
A56: Dispatched | B56: 4 | C56: # | D56: Delivery events dispatched from warehouse
A57: Received by Partners | B57: 3 | C57: # | D57: Confirmed received by implementing partners
A58: Last Mile Completed | B58: 2 | C58: # | D58: Completed to final beneficiaries
A59: Dispatch Rate % (auto) | B59: =IFERROR(B56/B55,"") -> 0.28571429 | C59: % | D59: Auto-calculated
A60: Partner Receipt Rate % (auto) | B60: =IFERROR(B57/B55,"") -> 0.21428571 | C60: % | D60: Auto-calculated
A61: Last Mile Rate % (auto) | B61: =IFERROR(B58/B55,"") -> 0.14285714 | C61: % | D61: Auto-calculated
A62: Main Transport Mode | B62: Road + Air | D62: e.g. Road, River, Air, Sea, Mixed
A63: Last Mile Partner 1 | B63: WFP
A64: Last Mile Partner 2 | B64: ACF
A65: Last Mile Partner 3 | B65: IRC
A66: Last Mile Partner 4
A68: ▌ SECTION 6 — SC PERFORMANCE KPIs
A69: On-Time Delivery Rate | B69: 0.44 | C69: % | D69: % of deliveries on time vs. planned schedule
A70: Stockout Risk Level | B70: High | D70: Select stockout risk assessment
A71: SC Overall Assessment | D71: Traffic-light assessment of overall SC health
A72: SC Comments / Notes | D72: Key issues, highlights, actions needed
A74: ▌ SECTION 7 — RISK REGISTER
A75: Risk # | B75: Risk Level | C75: Risk Description | D75: Mitigation Measure / Owner
A76: 1 | B76: High | C76: Rainy season access restrictions (Jul-Sep) | D76: Urgent pre-positioning by June — Country SC Coordinator
A77: 2 | B77: High | C77: Customs clearance delays averaging 45 days | D77: Engage customs authorities — MoU finalization — Procurement Officer
A78: 3 | B78: Medium | C78: Limited last-mile capacity in Lac region | D78: Identify additional implementing partners — Partnerships Officer
A79: 4
A80: 5
A81: 6
A82: 7
A83: 8
A85: GSCMTF | FAO — CSLO | Confidential — For Internal Use Only
A86: 🔵 Blue text = Manual input | ⚫ Black text = Auto-calculated formula | ⚡ = Fed by detail table below | Yellow bg = Input cell | Blue-tint bg = Formula cell
A89: ▌ SECTION 8 — BUDGET DETAIL | Enter each budget line here → feeds Section 1 (Budget Spent & Committed)
A90: # | B90: Budget Category | C90: Description / Activity | D90: Vendor / Supplier / Partner | E90: Reference / Contract # | F90: Amount (USD) | G90: Date | H90: Payment Status | I90: Notes / Remarks
A91: 1 | B91: Food Procurement | C91: Sorghum R1 | D91: SahelGrains | E91: PO-001 | F91: 920000 | G91: 45677 | H91: Spent
A92: 2 | B92: Food Procurement | C92: Cowpeas + Oil | D92: AFoodCo | E92: PO-002 | F92: 480000 | G92: 45693 | H92: Spent
A93: 3 | B93: Logistics & Transport | C93: Road transport N'Djamena | D93: TransSahel | E93: INV-010 | F93: 210000 | G93: 45703 | H93: Spent
A94: 4 | B94: Logistics & Transport | C94: Air cargo Abéché | D94: AirChad | E94: INV-020 | F94: 185000 | G94: 45717 | H94: Spent
A95: 5 | B95: Food Procurement | C95: CSB+ supply | D95: NutriAfrica | E95: PO-003 | F95: 560000 | G95: 45748 | H95: Committed
A96: 6 | B96: Warehousing | C96: Warehouse N'Djamena | D96: StoreTchad | E96: INV-030 | F96: 55000 | G96: 45717 | H96: Spent
A97: 7
A98: 8
A99: 9
A100: 10
A101: 11
A102: 12
A103: 13
A104: 14
A105: 15
A106: 16
A107: 17
A108: 18
... A125: 35
A126: TOTALS | F126: =IFERROR(SUM(F91:F125),0) -> 2410000
...

Sheet Colombia
A1: GSCMTF | US-OCHA Global Project — Colombia (COL) | Region: Latin America
A2: FAO Supply Chain Orchestration Unit (CSLO) | Confidential — Internal Use Only
A3: Last Updated: | C3: Updated by:
A5: ▌ SECTION 1 — PROGRAMMATIC INFORMATION
A6: Project Status | D6: Select current overall project status
A7: Total Budget (USD) | C7: USD | D7: Total budget allocated to this country
A8: Budget Spent to Date (auto) | B8: =IFERROR(SUMIF(H91:H125,"Spent",F91:F125),0) -> 0 | C8: USD | D8: ⚡ Auto-sum from Budget Detail table (Section 8)
A9: Budget Committed (auto) | B9: =IFERROR(SUMIF(H91:H125,"Committed",F91:F125),0) -> 0 | C9: USD | D9: ⚡ Auto-sum from Budget Detail table (Section 8)
A10: Budget Available (auto) | B10: =IFERROR(B7-B8-B9,"") -> 0 | C10: USD | D10: Auto-calculated: Total − Spent − Committed
A11: Budget Utilized % (auto) | B11: =IFERROR(B8/B7,"") | C11: % | D11: Auto-calculated
A12: Target Beneficiaries | C12: # | D12: Total number of targeted beneficiaries
A13: Beneficiaries Reached | C13: # | D13: Cumulative beneficiaries reached to date
A14: Beneficiary Coverage % (auto) | B14: =IFERROR(B13/B12,"") | C14: % | D14: Auto-calculated
A15: Total Distribution Months | C15: months | D15: Total planned distribution months
A16: Distributions Completed | C16: months | D16: Number of distribution months completed
A17: Distribution Progress % (auto) | B17: =IFERROR(B16/B15,"") | C17: % | D17: Auto-calculated
A18: Next Distribution Date | C18: date | D18: Planned date of next distribution
A19: Project Start Date | C19: date | D19: Official project start date
A20: Project End Date | C20: date | D20: Official project end date
A21: Project Officer (FAO) | D21: Name of responsible FAO Project Officer
A22: FAO Country Office | D22: FAO country office responsible for implementation
A24: ▌ SECTION 2 — COMMODITIES / ITEMS DISTRIBUTED
A25: Commodity / Item 1 | C25: name | D25: e.g. Rice, Lentils, Cooking Oil, CSB+, Soap, NFIs…
A26: Commodity / Item 2 | C26: name | D26: e.g. Rice, Lentils, Cooking Oil, CSB+, Soap, NFIs…
A27: Commodity / Item 3 | C27: name | D27: e.g. Rice, Lentils, Cooking Oil, CSB+, Soap, NFIs…
A28: Commodity / Item 4 | C28: name | D28: e.g. Rice, Lentils, Cooking Oil, CSB+, Soap, NFIs…
A29: Commodity / Item 5 | C29: name | D29: e.g. Rice, Lentils, Cooking Oil, CSB+, Soap, NFIs…
A30: Commodity / Item 6 | C30: name | D30: e.g. Rice, Lentils, Cooking Oil, CSB+, Soap, NFIs…
A31: Commodity / Item 7 | C31: name | D31: e.g. Rice, Lentils, Cooking Oil, CSB+, Soap, NFIs…
A32: Commodity / Item 8 | C32: name | D32: e.g. Rice, Lentils, Cooking Oil, CSB+, Soap, NFIs…
A34: ▌ SECTION 3 — SUPPLY CHAIN: ORDERS (auto-counted from Section 9 detail table)
A35: Orders — Pending (auto) | B35: =IFERROR(COUNTIF(M129:M178,"Pending"),0) -> 0 | C35: # | D35: ⚡ Auto-count from Orders Detail table (Section 9)
A36: Orders — Confirmed (auto) | B36: =IFERROR(COUNTIF(M129:M178,"Confirmed"),0) -> 0 | C36: # | D36: ⚡ Auto-count from Orders Detail table (Section 9)
A37: Orders — In Production (auto) | B37: =IFERROR(COUNTIF(M129:M178,"In Production"),0) -> 0 | C37: # | D37: ⚡ Auto-count from Orders Detail table (Section 9)
A38: Orders — Shipped (auto) | B38: =IFERROR(COUNTIF(M129:M178,"Shipped"),0) -> 0 | C38: # | D38: ⚡ Auto-count from Orders Detail table (Section 9)
A39: Orders — Delivered (auto) | B39: =IFERROR(COUNTIF(M129:M178,"Delivered"),0) -> 0 | C39: # | D39: ⚡ Auto-count from Orders Detail table (Section 9)
A40: Total Orders (auto) | B40: =IFERROR(SUM(B35:B39),0) -> 0 | C40: # | D40: Auto-calculated: sum of all pipeline stages
A41: Order Fulfillment Rate | C41: % | D41: Manual KPI: % of expected orders fulfilled to date
A43: ▌ SECTION 4 — SUPPLY CHAIN: INVENTORY
A44: Stock On Hand | C44: MT | D44: Physical stock in FAO warehouses
A45: Stock In Transit | C45: MT | D45: Stock en route to destination warehouses
A46: Total Stock (auto) | B46: =IFERROR(B44+B45,"") -> 0 | C46: MT | D46: Auto-calculated
A47: Warehouse Capacity (total) | C47: MT | D47: Total warehouse capacity available
A48: Capacity Utilization % (auto) | B48: =IFERROR((B44+B45)/B47,"") | C48: % | D48: Auto-calculated
A49: Warehouse Location 1 | C49: city | D49: Main hub
A50: Warehouse Location 2 | C50: city | D50: Secondary hub (if applicable)
A51: Warehouse Location 3 | C51: city
A52: Warehouse Location 4 | C52: city
A54: ▌ SECTION 5 — SUPPLY CHAIN: DELIVERIES & LAST MILE
A55: Planned Deliveries (total) | C55: # | D55: Total delivery events planned
A56: Dispatched | C56: # | D56: Delivery events dispatched from warehouse
A57: Received by Partners | C57: # | D57: Confirmed received by implementing partners
A58: Last Mile Completed | C58: # | D58: Completed to final beneficiaries
A59: Dispatch Rate % (auto) | B59: =IFERROR(B56/B55,"") | C59: % | D59: Auto-calculated
A60: Partner Receipt Rate % (auto) | B60: =IFERROR(B57/B55,"") | C60: % | D60: Auto-calculated
A61: Last Mile Rate % (auto) | B61: =IFERROR(B58/B55,"") | C61: % | D61: Auto-calculated
A62: Main Transport Mode | D62: e.g. Road, River, Air, Sea, Mixed
A63: Last Mile Partner 1
A64: Last Mile Partner 2
A65: Last Mile Partner 3
A66: Last Mile Partner 4
A68: ▌ SECTION 6 — SC PERFORMANCE KPIs
A69: On-Time Delivery Rate | C69: % | D69: % of deliveries on time vs. planned schedule
A70: Stockout Risk Level | D70: Select stockout risk assessment
A71: SC Overall Assessment | D71: Traffic-light assessment of overall SC health
A72: SC Comments / Notes | D72: Key issues, highlights, actions needed
A74: ▌ SECTION 7 — RISK REGISTER
A75: Risk # | B75: Risk Level | C75: Risk Description | D75: Mitigation Measure / Owner
A76: 1
A77: 2
A78: 3
A79: 4
A80: 5
A81: 6
A82: 7
A83: 8
A85: GSCMTF | FAO — CSLO | Confidential — For Internal Use Only
A86: 🔵 Blue text = Manual input | ⚫ Black text = Auto-calculated formula | ⚡ = Fed by detail table below | Yellow bg = Input cell | Blue-tint bg = Formula cell
A89: ▌ SECTION 8 — BUDGET DETAIL | Enter each budget line here → feeds Section 1 (Budget Spent & Committed)
A90: # | B90: Budget Category | C90: Description / Activity | D90: Vendor / Supplier / Partner | E90: Reference / Contract # | F90: Amount (USD) | G90: Date | H90: Payment Status | I90: Notes / Remarks
A91: 1
A92: 2
A93: 3
A94: 4
A95: 5
A96: 6
A97: 7
A98: 8
A99: 9
A100: 10
A101: 11
A102: 12
... A125: 35
A126: TOTALS | F126: =IFERROR(SUM(F91:F125),0) -> 0
A127: ▌ SECTION 9 — ORDERS DETAIL | Enter each order here → feeds Section 3 order pipeline counts
A128: # | B128: Order Ref / PO # | C128: Commodity / Item | D128: Unit | E128: Qty Ordered | F128: Qty Received | G128: Unit Cost (USD) | H128: Total Value (auto, USD) | I128: Supplier | J128: PO / Confirm. Date | K128: Expected Delivery | L128: Actual Delivery | M128: Status | N128: Notes
A129: 1 | H129: =IFERROR(E129*G129,"") -> 0
A130: 2 | H130: =IFERROR(E130*G130,"") -> 0
A131: 3 | H131: =IFERROR(E131*G131,"") -> 0
A132: 4 | H132: =IFERROR(E132*G132,"") -> 0
...

Sheet DRC
A1: GSCMTF | US-OCHA Global Project — DRC (COD) | Region: Central Africa
A2: FAO Supply Chain Orchestration Unit (CSLO) | Confidential — Internal Use Only
A3: Last Updated: | C3: Updated by:
A5: ▌ SECTION 1 — PROGRAMMATIC INFORMATION
A6: Project Status | D6: Select current overall project status
A7: Total Budget (USD) | C7: USD | D7: Total budget allocated to this country
A8: Budget Spent to Date (auto) | B8: =IFERROR(SUMIF(H91:H125,"Spent",F91:F125),0) -> 0 | C8: USD | D8: ⚡ Auto-sum from Budget Detail table (Section 8)
A9: Budget Committed (auto) | B9: =IFERROR(SUMIF(H91:H125,"Committed",F91:F125),0) -> 0 | C9: USD | D9: ⚡ Auto-sum from Budget Detail table (Section 8)
A10: Budget Available (auto) | B10: =IFERROR(B7-B8-B9,"") -> 0 | C10: USD | D10: Auto-calculated: Total − Spent − Committed
A11: Budget Utilized % (auto) | B11: =IFERROR(B8/B7,"") | C11: % | D11: Auto-calculated
A12: Target Beneficiaries | C12: # | D12: Total number of targeted beneficiaries
A13: Beneficiaries Reached | C13: # | D13: Cumulative beneficiaries reached to date
A14: Beneficiary Coverage % (auto) | B14: =IFERROR(B13/B12,"") | C14: % | D14: Auto-calculated
A15: Total Distribution Months | C15: months | D15: Total planned distribution months
A16: Distributions Completed | C16: months | D16: Number of distribution months completed
A17: Distribution Progress % (auto) | B17: =IFERROR(B16/B15,"") | C17: % | D17: Auto-calculated
A18: Next Distribution Date | C18: date | D18: Planned date of next distribution
A19: Project Start Date | C19: date | D19: Official project start date
A20: Project End Date | C20: date | D20: Official project end date
A21: Project Officer (FAO) | D21: Name of responsible FAO Project Officer
A22: FAO Country Office | D22: FAO country office responsible for implementation
A24: ▌ SECTION 2 — COMMODITIES / ITEMS DISTRIBUTED
A25: Commodity / Item 1 | C25: name | D25: e.g. Rice, Lentils, Cooking Oil, CSB+, Soap, NFIs…
A26: Commodity / Item 2 | C26: name | D26: e.g. Rice, Lentils, Cooking Oil, CSB+, Soap, NFIs…
A27: Commodity / Item 3 | C27: name | D27: e.g. Rice, Lentils, Cooking Oil, CSB+, Soap, NFIs…
A28: Commodity / Item 4 | C28: name | D28: e.g. Rice, Lentils, Cooking Oil, CSB+, Soap, NFIs…
A29: Commodity / Item 5 | C29: name | D29: e.g. Rice, Lentils, Cooking Oil, CSB+, Soap, NFIs…
A30: Commodity / Item 6 | C30: name | D30: e.g. Rice, Lentils, Cooking Oil, CSB+, Soap, NFIs…
A31: Commodity / Item 7 | C31: name | D31: e.g. Rice, Lentils, Cooking Oil, CSB+, Soap, NFIs…
A32: Commodity / Item 8 | C32: name | D32: e.g. Rice, Lentils, Cooking Oil, CSB+, Soap, NFIs…
A34: ▌ SECTION 3 — SUPPLY CHAIN: ORDERS (auto-counted from Section 9 detail table)
A35: Orders — Pending (auto) | B35: =IFERROR(COUNTIF(M129:M178,"Pending"),0) -> 0 | C35: # | D35: ⚡ Auto-count from Orders Detail table (Section 9)
A36: Orders — Confirmed (auto) | B36: =IFERROR(COUNTIF(M129:M178,"Confirmed"),0) -> 0 | C36: # | D36: ⚡ Auto-count from Orders Detail table (Section 9)
A37: Orders — In Production (auto) | B37: =IFERROR(COUNTIF(M129:M178,"In Production"),0) -> 0 | C37: # | D37: ⚡ Auto-count from Orders Detail table (Section 9)
A38: Orders — Shipped (auto) | B38: =IFERROR(COUNTIF(M129:M178,"Shipped"),0) -> 0 | C38: # | D38: ⚡ Auto-count from Orders Detail table (Section 9)
A39: Orders — Delivered (auto) | B39: =IFERROR(COUNTIF(M129:M178,"Delivered"),0) -> 0 | C39: # | D39: ⚡ Auto-count from Orders Detail table (Section 9)
A40: Total Orders (auto) | B40: =IFERROR(SUM(B35:B39),0) -> 0 | C40: # | D40: Auto-calculated: sum of all pipeline stages
A41: Order Fulfillment Rate | C41: % | D41: Manual KPI: % of expected orders fulfilled to date
A43: ▌ SECTION 4 — SUPPLY CHAIN: INVENTORY
A44: Stock On Hand | C44: MT | D44: Physical stock in FAO warehouses
A45: Stock In Transit | C45: MT | D45: Stock en route to destination warehouses
A46: Total Stock (auto) | B46: =IFERROR(B44+B45,"") -> 0 | C46: MT | D46: Auto-calculated
A47: Warehouse Capacity (total) | C47: MT | D47: Total warehouse capacity available
A48: Capacity Utilization % (auto) | B48: =IFERROR((B44+B45)/B47,"") | C48: % | D48: Auto-calculated
A49: Warehouse Location 1 | C49: city | D49: Main hub
A50: Warehouse Location 2 | C50: city | D50: Secondary hub (if applicable)
A51: Warehouse Location 3 | C51: city
A52: Warehouse Location 4 | C52: city
A54: ▌ SECTION 5 — SUPPLY CHAIN: DELIVERIES & LAST MILE
A55: Planned Deliveries (total) | C55: # | D55: Total delivery events planned
A56: Dispatched | C56: # | D56: Delivery events dispatched from warehouse
A57: Received by Partners | C57: # | D57: Confirmed received by implementing partners
A58: Last Mile Completed | C58: # | D58: Completed to final beneficiaries
A59: Dispatch Rate % (auto) | B59: =IFERROR(B56/B55,"") | C59: % | D59: Auto-calculated
A60: Partner Receipt Rate % (auto) | B60: =IFERROR(B57/B55,"") | C60: % | D60: Auto-calculated
A61: Last Mile Rate % (auto) | B61: =IFERROR(B58/B55,"") | C61: % | D61: Auto-calculated
A62: Main Transport Mode | D62: e.g. Road, River, Air, Sea, Mixed
A63: Last Mile Partner 1
A64: Last Mile Partner 2
A65: Last Mile Partner 3
A66: Last Mile Partner 4
A68: ▌ SECTION 6 — SC PERFORMANCE KPIs
A69: On-Time Delivery Rate | C69: % | D69: % of deliveries on time vs. planned schedule
A70: Stockout Risk Level | D70: Select stockout risk assessment
A71: SC Overall Assessment | D71: Traffic-light assessment of overall SC health
A72: SC Comments / Notes | D72: Key issues, highlights, actions needed
A74: ▌ SECTION 7 — RISK REGISTER
A75: Risk # | B75: Risk Level | C75: Risk Description | D75: Mitigation Measure / Owner
A76: 1
A77: 2
A78: 3
A79: 4
A80: 5
A81: 6
A82: 7
A83: 8
A85: GSCMTF | FAO — CSLO | Confidential — For Internal Use Only
A86: 🔵 Blue text = Manual input | ⚫ Black text = Auto-calculated formula | ⚡ = Fed by detail table below | Yellow bg = Input cell | Blue-tint bg = Formula cell
A89: ▌ SECTION 8 — BUDGET DETAIL | Enter each budget line here → feeds Section 1 (Budget Spent & Committed)
A90: # | B90: Budget Category | C90: Description / Activity | D90: Vendor / Supplier / Partner | E90: Reference / Contract # | F90: Amount (USD) | G90: Date | H90: Payment Status | I90: Notes / Remarks
A91: 1
A92: 2
A93: 3
A94: 4
A95: 5
A96: 6
A97: 7
A98: 8
A99: 9
A100: 10
A101: 11
A102: 12
... A125: 35
A126: TOTALS | F126: =IFERROR(SUM(F91:F125),0) -> 0
A127: ▌ SECTION 9 — ORDERS DETAIL | Enter each order here → feeds Section 3 order pipeline counts
A128: # | B128: Order Ref / PO # | C128: Commodity / Item | D128: Unit | E128: Qty Ordered | F128: Qty Received | G128: Unit Cost (USD) | H128: Total Value (auto, USD) | I128: Supplier | J128: PO / Confirm. Date | K128: Expected Delivery | L128: Actual Delivery | M128: Status | N128: Notes
A129: 1 | H129: =IFERROR(E129*G129,"") -> 0
A130: 2 | H130: =IFERROR(E130*G130,"") -> 0
A131: 3 | H131: =IFERROR(E131*G131,"") -> 0
A132: 4 | H132: =IFERROR(E132*G132,"") -> 0
...

Sheet Ethiopia
A1: GSCMTF | US-OCHA Global Project — Ethiopia (ETH) | Region: East Africa
A2: FAO Supply Chain Orchestration Unit (CSLO) | Confidential — Internal Use Only
A3: Last Updated: | C3: Updated by:
A5: ▌ SECTION 1 — PROGRAMMATIC INFORMATION
A6: Project Status | D6: Select current overall project status
A7: Total Budget (USD) | C7: USD | D7: Total budget allocated to this country
A8: Budget Spent to Date (auto) | B8: =IFERROR(SUMIF(H91:H125,"Spent",F91:F125),0) -> 0 | C8: USD | D8: ⚡ Auto-sum from Budget Detail table (Section 8)
A9: Budget Committed (auto) | B9: =IFERROR(SUMIF(H91:H125,"Committed",F91:F125),0) -> 0 | C9: USD | D9: ⚡ Auto-sum from Budget Detail table (Section 8)
A10: Budget Available (auto) | B10: =IFERROR(B7-B8-B9,"") -> 0 | C10: USD | D10: Auto-calculated: Total − Spent − Committed
A11: Budget Utilized % (auto) | B11: =IFERROR(B8/B7,"") | C11: % | D11: Auto-calculated
A12: Target Beneficiaries | C12: # | D12: Total number of targeted beneficiaries
A13: Beneficiaries Reached | C13: # | D13: Cumulative beneficiaries reached to date
A14: Beneficiary Coverage % (auto) | B14: =IFERROR(B13/B12,"") | C14: % | D14: Auto-calculated
A15: Total Distribution Months | C15: months | D15: Total planned distribution months
A16: Distributions Completed | C16: months | D16: Number of distribution months completed
A17: Distribution Progress % (auto) | B17: =IFERROR(B16/B15,"") | C17: % | D17: Auto-calculated
A18: Next Distribution Date | C18: date | D18: Planned date of next distribution
A19: Project Start Date | C19: date | D19: Official project start date
A20: Project End Date | C20: date | D20: Official project end date
A21: Project Officer (FAO) | D21: Name of responsible FAO Project Officer
A22: FAO Country Office | D22: FAO country office responsible for implementation
A24: ▌ SECTION 2 — COMMODITIES / ITEMS DISTRIBUTED
A25: Commodity / Item 1 | C25: name | D25: e.g. Rice, Lentils, Cooking Oil, CSB+, Soap, NFIs…
A26: Commodity / Item 2 | C26: name | D26: e.g. Rice, Lentils, Cooking Oil, CSB+, Soap, NFIs…
A27: Commodity / Item 3 | C27: name | D27: e.g. Rice, Lentils, Cooking Oil, CSB+, Soap, NFIs…
A28: Commodity / Item 4 | C28: name | D28: e.g. Rice, Lentils, Cooking Oil, CSB+, Soap, NFIs…
A29: Commodity / Item 5 | C29: name | D29: e.g. Rice, Lentils, Cooking Oil, CSB+, Soap, NFIs…
A30: Commodity / Item 6 | C30: name | D30: e.g. Rice, Lentils, Cooking Oil, CSB+, Soap, NFIs…
A31: Commodity / Item 7 | C31: name | D31: e.g. Rice, Lentils, Cooking Oil, CSB+, Soap, NFIs…
A32: Commodity / Item 8 | C32: name | D32: e.g. Rice, Lentils, Cooking Oil, CSB+, Soap, NFIs…
A34: ▌ SECTION 3 — SUPPLY CHAIN: ORDERS (auto-counted from Section 9 detail table)
A35: Orders — Pending (auto) | B35: =IFERROR(COUNTIF(M129:M178,"Pending"),0) -> 0 | C35: # | D35: ⚡ Auto-count from Orders Detail table (Section 9)
A36: Orders — Confirmed (auto) | B36: =IFERROR(COUNTIF(M129:M178,"Confirmed"),0) -> 0 | C36: # | D36: ⚡ Auto-count from Orders Detail table (Section 9)
A37: Orders — In Production (auto) | B37: =IFERROR(COUNTIF(M129:M178,"In Production"),0) -> 0 | C37: # | D37: ⚡ Auto-count from Orders Detail table (Section 9)
A38: Orders — Shipped (auto) | B38: =IFERROR(COUNTIF(M129:M178,"Shipped"),0) -> 0 | C38: # | D38: ⚡ Auto-count from Orders Detail table (Section 9)
A39: Orders — Delivered (auto) | B39: =IFERROR(COUNTIF(M129:M178,"Delivered"),0) -> 0 | C39: # | D39: ⚡ Auto-count from Orders Detail table (Section 9)
A40: Total Orders (auto) | B40: =IFERROR(SUM(B35:B39),0) -> 0 | C40: # | D40: Auto-calculated: sum of all pipeline stages
A41: Order Fulfillment Rate | C41: % | D41: Manual KPI: % of expected orders fulfilled to date
A43: ▌ SECTION 4 — SUPPLY CHAIN: INVENTORY
A44: Stock On Hand | C44: MT | D44: Physical stock in FAO warehouses
A45: Stock In Transit | C45: MT | D45: Stock en route to destination warehouses
A46: Total Stock (auto) | B46: =IFERROR(B44+B45,"") -> 0 | C46: MT | D46: Auto-calculated
A47: Warehouse Capacity (total) | C47: MT | D47: Total warehouse capacity available
A48: Capacity Utilization % (auto) | B48: =IFERROR((B44+B45)/B47,"") | C48: % | D48: Auto-calculated
A49: Warehouse Location 1 | C49: city | D49: Main hub
A50: Warehouse Location 2 | C50: city | D50: Secondary hub (if applicable)
A51: Warehouse Location 3 | C51: city
A52: Warehouse Location 4 | C52: city
A54: ▌ SECTION 5 — SUPPLY CHAIN: DELIVERIES & LAST MILE
A55: Planned Deliveries (total) | C55: # | D55: Total delivery events planned
A56: Dispatched | C56: # | D56: Delivery events dispatched from warehouse
A57: Received by Partners | C57: # | D57: Confirmed received by implementing partners
A58: Last Mile Completed | C58: # | D58: Completed to final beneficiaries
A59: Dispatch Rate % (auto) | B59: =IFERROR(B56/B55,"") | C59: % | D59: Auto-calculated
A60: Partner Receipt Rate % (auto) | B60: =IFERROR(B57/B55,"") | C60: % | D60: Auto-calculated
A61: Last Mile Rate % (auto) | B61: =IFERROR(B58/B55,"") | C61: % | D61: Auto-calculated
A62: Main Transport Mode | D62: e.g. Road, River, Air, Sea, Mixed
A63: Last Mile Partner 1
A64: Last Mile Partner 2
A65: Last Mile Partner 3
A66: Last Mile Partner 4
A68: ▌ SECTION 6 — SC PERFORMANCE KPIs
A69: On-Time Delivery Rate | C69: % | D69: % of deliveries on time vs. planned schedule
A70: Stockout Risk Level | D70: Select stockout risk assessment
A71: SC Overall Assessment | D71: Traffic-light assessment of overall SC health
A72: SC Comments / Notes | D72: Key issues, highlights, actions needed
A74: ▌ SECTION 7 — RISK REGISTER
A75: Risk # | B75: Risk Level | C75: Risk Description | D75: Mitigation Measure / Owner
A76: 1
A77: 2
A78: 3
A79: 4
A80: 5
A81: 6
A82: 7
A83: 8
A85: GSCMTF | FAO — CSLO | Confidential — For Internal Use Only
A86: 🔵 Blue text = Manual input | ⚫ Black text = Auto-calculated formula | ⚡ = Fed by detail table below | Yellow bg = Input cell | Blue-tint bg = Formula cell
A89: ▌ SECTION 8 — BUDGET DETAIL | Enter each budget line here → feeds Section 1 (Budget Spent & Committed)
A90: # | B90: Budget Category | C90: Description / Activity | D90: Vendor / Supplier / Partner | E90: Reference / Contract # | F90: Amount (USD) | G90: Date | H90: Payment Status | I90: Notes / Remarks
A91: 1
A92: 2
A93: 3
A94: 4
A95: 5
A96: 6
A97: 7
A98: 8
A99: 9
A100: 10
A101: 11
A102: 12
... A125: 35
A126: TOTALS | F126: =IFERROR(SUM(F91:F125),0) -> 0
A127: ▌ SECTION 9 — ORDERS DETAIL | Enter each order here → feeds Section 3 order pipeline counts
A128: # | B128: Order Ref / PO # | C128: Commodity / Item | D128: Unit | E128: Qty Ordered | F128: Qty Received | G128: Unit Cost (USD) | H128: Total Value (auto, USD) | I128: Supplier | J128: PO / Confirm. Date | K128: Expected Delivery | L128: Actual Delivery | M128: Status | N128: Notes
A129: 1 | H129: =IFERROR(E129*G129,"") -> 0
A130: 2 | H130: =IFERROR(E130*G130,"") -> 0
A131: 3 | H131: =IFERROR(E131*G131,"") -> 0
A132: 4 | H132: =IFERROR(E132*G132,"") -> 0
...

Sheet Haiti
A1: GSCMTF | US-OCHA Global Project — Haiti (HTI) | Region: Caribbean
A2: FAO Supply Chain Orchestration Unit (CSLO) | Confidential — Internal Use Only
A3: Last Updated: | C3: Updated by:
A5: ▌ SECTION 1 — PROGRAMMATIC INFORMATION
A6: Project Status | D6: Select current overall project status
A7: Total Budget (USD) | C7: USD | D7: Total budget allocated to this country
A8: Budget Spent to Date (auto) | B8: =IFERROR(SUMIF(H91:H125,"Spent",F91:F125),0) -> 0 | C8: USD | D8: ⚡ Auto-sum from Budget Detail table (Section 8)
A9: Budget Committed (auto) | B9: =IFERROR(SUMIF(H91:H125,"Committed",F91:F125),0) -> 0 | C9: USD | D9: ⚡ Auto-sum from Budget Detail table (Section 8)
A10: Budget Available (auto) | B10: =IFERROR(B7-B8-B9,"") -> 0 | C10: USD | D10: Auto-calculated: Total − Spent − Committed
A11: Budget Utilized % (auto) | B11: =IFERROR(B8/B7,"") | C11: % | D11: Auto-calculated
A12: Target Beneficiaries | C12: # | D12: Total number of targeted beneficiaries
A13: Beneficiaries Reached | C13: # | D13: Cumulative beneficiaries reached to date
A14: Beneficiary Coverage % (auto) | B14: =IFERROR(B13/B12,"") | C14: % | D14: Auto-calculated
A15: Total Distribution Months | C15: months | D15: Total planned distribution months
A16: Distributions Completed | C16: months | D16: Number of distribution months completed
A17: Distribution Progress % (auto) | B17: =IFERROR(B16/B15,"") | C17: % | D17: Auto-calculated
A18: Next Distribution Date | C18: date | D18: Planned date of next distribution
A19: Project Start Date | C19: date | D19: Official project start date
A20: Project End Date | C20: date | D20: Official project end date
A21: Project Officer (FAO) | D21: Name of responsible FAO Project Officer
A22: FAO Country Office | D22: FAO country office responsible for implementation
A24: ▌ SECTION 2 — COMMODITIES / ITEMS DISTRIBUTED
A25: Commodity / Item 1 | C25: name | D25: e.g. Rice, Lentils, Cooking Oil, CSB+, Soap, NFIs…
A26: Commodity / Item 2 | C26: name | D26: e.g. Rice, Lentils, Cooking Oil, CSB+, Soap, NFIs…
A27: Commodity / Item 3 | C27: name | D27: e.g. Rice, Lentils, Cooking Oil, CSB+, Soap, NFIs…
A28: Commodity / Item 4 | C28: name | D28: e.g. Rice, Lentils, Cooking Oil, CSB+, Soap, NFIs…
A29: Commodity / Item 5 | C29: name | D29: e.g. Rice, Lentils, Cooking Oil, CSB+, Soap, NFIs…
A30: Commodity / Item 6 | C30: name | D30: e.g. Rice, Lentils, Cooking Oil, CSB+, Soap, NFIs…
A31: Commodity / Item 7 | C31: name | D31: e.g. Rice, Lentils, Cooking Oil, CSB+, Soap, NFIs…
A32: Commodity / Item 8 | C32: name | D32: e.g. Rice, Lentils, Cooking Oil, CSB+, Soap, NFIs…
A34: ▌ SECTION 3 — SUPPLY CHAIN: ORDERS (auto-counted from Section 9 detail table)
A35: Orders — Pending (auto) | B35: =IFERROR(COUNTIF(M129:M178,"Pending"),0) -> 0 | C35: # | D35: ⚡ Auto-count from Orders Detail table (Section 9)
A36: Orders — Confirmed (auto) | B36: =IFERROR(COUNTIF(M129:M178,"Confirmed"),0) -> 0 | C36: # | D36: ⚡ Auto-count from Orders Detail table (Section 9)
A37: Orders — In Production (auto) | B37: =IFERROR(COUNTIF(M129:M178,"In Production"),0) -> 0 | C37: # | D37: ⚡ Auto-count from Orders Detail table (Section 9)
A38: Orders — Shipped (auto) | B38: =IFERROR(COUNTIF(M129:M178,"Shipped"),0) -> 0 | C38: # | D38: ⚡ Auto-count from Orders Detail table (Section 9)
A39: Orders — Delivered (auto) | B39: =IFERROR(COUNTIF(M129:M178,"Delivered"),0) -> 0 | C39: # | D39: ⚡ Auto-count from Orders Detail table (Section 9)
A40: Total Orders (auto) | B40: =IFERROR(SUM(B35:B39),0) -> 0 | C40: # | D40: Auto-calculated: sum of all pipeline stages
A41: Order Fulfillment Rate | C41: % | D41: Manual KPI: % of expected orders fulfilled to date
A43: ▌ SECTION 4 — SUPPLY CHAIN: INVENTORY
A44: Stock On Hand | C44: MT | D44: Physical stock in FAO warehouses
A45: Stock In Transit | C45: MT | D45: Stock en route to destination warehouses
A46: Total Stock (auto) | B46: =IFERROR(B44+B45,"") -> 0 | C46: MT | D46: Auto-calculated
A47: Warehouse Capacity (total) | C47: MT | D47: Total warehouse capacity available
A48: Capacity Utilization % (auto) | B48: =IFERROR((B44+B45)/B47,"") | C48: % | D48: Auto-calculated
A49: Warehouse Location 1 | C49: city | D49: Main hub
A50: Warehouse Location 2 | C50: city | D50: Secondary hub (if applicable)
A51: Warehouse Location 3 | C51: city
A52: Warehouse Location 4 | C52: city
A54: ▌ SECTION 5 — SUPPLY CHAIN: DELIVERIES & LAST MILE
A55: Planned Deliveries (total) | C55: # | D55: Total delivery events planned
A56: Dispatched | C56: # | D56: Delivery events dispatched from warehouse
A57: Received by Partners | C57: # | D57: Confirmed received by implementing partners
A58: Last Mile Completed | C58: # | D58: Completed to final beneficiaries
A59: Dispatch Rate % (auto) | B59: =IFERROR(B56/B55,"") | C59: % | D59: Auto-calculated
A60: Partner Receipt Rate % (auto) | B60: =IFERROR(B57/B55,"") | C60: % | D60: Auto-calculated
A61: Last Mile Rate % (auto) | B61: =IFERROR(B58/B55,"") | C61: % | D61: Auto-calculated
A62: Main Transport Mode | D62: e.g. Road, River, Air, Sea, Mixed
A63: Last Mile Partner 1
A64: Last Mile Partner 2
A65: Last Mile Partner 3
A66: Last Mile Partner 4
A68: ▌ SECTION 6 — SC PERFORMANCE KPIs
A69: On-Time Delivery Rate | C69: % | D69: % of deliveries on time vs. planned schedule
A70: Stockout Risk Level | D70: Select stockout risk assessment
A71: SC Overall Assessment | D71: Traffic-light assessment of overall SC health
A72: SC Comments / Notes | D72: Key issues, highlights, actions needed
A74: ▌ SECTION 7 — RISK REGISTER
A75: Risk # | B75: Risk Level | C75: Risk Description | D75: Mitigation Measure / Owner
A76: 1
A77: 2
A78: 3
A79: 4
A80: 5
A81: 6
A82: 7
A83: 8
A85: GSCMTF | FAO — CSLO | Confidential — For Internal Use Only
A86: 🔵 Blue text = Manual input | ⚫ Black text = Auto-calculated formula | ⚡ = Fed by detail table below | Yellow bg = Input cell | Blue-tint bg = Formula cell
A89: ▌ SECTION 8 — BUDGET DETAIL | Enter each budget line here → feeds Section 1 (Budget Spent & Committed)
A90: # | B90: Budget Category | C90: Description / Activity | D90: Vendor / Supplier / Partner | E90: Reference / Contract # | F90: Amount (USD) | G90: Date | H90: Payment Status | I90: Notes / Remarks
A91: 1
A92: 2
A93: 3
A94: 4
A95: 5
A96: 6
A97: 7
A98: 8
A99: 9
A100: 10
A101: 11
A102: 12
... A125: 35
A126: TOTALS | F126: =IFERROR(SUM(F91:F125),0) -> 0
A127: ▌ SECTION 9 — ORDERS DETAIL | Enter each order here → feeds Section 3 order pipeline counts
A128: # | B128: Order Ref / PO # | C128: Commodity / Item | D128: Unit | E128: Qty Ordered | F128: Qty Received | G128: Unit Cost (USD) | H128: Total Value (auto, USD) | I128: Supplier | J128: PO / Confirm. Date | K128: Expected Delivery | L128: Actual Delivery | M128: Status | N128: Notes
A129: 1 | H129: =IFERROR(E129*G129,"") -> 0
A130: 2 | H130: =IFERROR(E130*G130,"") -> 0
A131: 3 | H131: =IFERROR(E131*G131,"") -> 0
A132: 4 | H132: =IFERROR(E132*G132,"") -> 0
...

Sheet Honduras
A1: GSCMTF | US-OCHA Global Project — Honduras (HND) | Region: Central America
A2: FAO Supply Chain Orchestration Unit (CSLO) | Confidential — Internal Use Only
A3: Last Updated: | C3: Updated by:
A5: ▌ SECTION 1 — PROGRAMMATIC INFORMATION
A6: Project Status | D6: Select current overall project status
A7: Total Budget (USD) | C7: USD | D7: Total budget allocated to this country
A8: Budget Spent to Date (auto) | B8: =IFERROR(SUMIF(H91:H125,"Spent",F91:F125),0) -> 0 | C8: USD | D8: ⚡ Auto-sum from Budget Detail table (Section 8)
A9: Budget Committed (auto) | B9: =IFERROR(SUMIF(H91:H125,"Committed",F91:F125),0) -> 0 | C9: USD | D9: ⚡ Auto-sum from Budget Detail table (Section 8)
A10: Budget Available (auto) | B10: =IFERROR(B7-B8-B9,"") -> 0 | C10: USD | D10: Auto-calculated: Total − Spent − Committed
A11: Budget Utilized % (auto) | B11: =IFERROR(B8/B7,"") | C11: % | D11: Auto-calculated
A12: Target Beneficiaries | C12: # | D12: Total number of targeted beneficiaries
A13: Beneficiaries Reached | C13: # | D13: Cumulative beneficiaries reached to date
A14: Beneficiary Coverage % (auto) | B14: =IFERROR(B13/B12,"") | C14: % | D14: Auto-calculated
A15: Total Distribution Months | C15: months | D15: Total planned distribution months
A16: Distributions Completed | C16: months | D16: Number of distribution months completed
A17: Distribution Progress % (auto) | B17: =IFERROR(B16/B15,"") | C17: % | D17: Auto-calculated
A18: Next Distribution Date | C18: date | D18: Planned date of next distribution
A19: Project Start Date | C19: date | D19: Official project start date
A20: Project End Date | C20: date | D20: Official project end date
A21: Project Officer (FAO) | D21: Name of responsible FAO Project Officer
A22: FAO Country Office | D22: FAO country office responsible for implementation
A24: ▌ SECTION 2 — COMMODITIES / ITEMS DISTRIBUTED
A25: Commodity / Item 1 | C25: name | D25: e.g. Rice, Lentils, Cooking Oil, CSB+, Soap, NFIs…
A26: Commodity / Item 2 | C26: name | D26: e.g. Rice, Lentils, Cooking Oil, CSB+, Soap, NFIs…
A27: Commodity / Item 3 | C27: name | D27: e.g. Rice, Lentils, Cooking Oil, CSB+, Soap, NFIs…
A28: Commodity / Item 4 | C28: name | D28: e.g. Rice, Lentils, Cooking Oil, CSB+, Soap, NFIs…
A29: Commodity / Item 5 | C29: name | D29: e.g. Rice, Lentils, Cooking Oil, CSB+, Soap, NFIs…
A30: Commodity / Item 6 | C30: name | D30: e.g. Rice, Lentils, Cooking Oil, CSB+, Soap, NFIs…
A31: Commodity / Item 7 | C31: name | D31: e.g. Rice, Lentils, Cooking Oil, CSB+, Soap, NFIs…
A32: Commodity / Item 8 | C32: name | D32: e.g. Rice, Lentils, Cooking Oil, CSB+, Soap, NFIs…
A34: ▌ SECTION 3 — SUPPLY CHAIN: ORDERS (auto-counted from Section 9 detail table)
A35: Orders — Pending (auto) | B35: =IFERROR(COUNTIF(M129:M178,"Pending"),0) -> 0 | C35: # | D35: ⚡ Auto-count from Orders Detail table (Section 9)
A36: Orders — Confirmed (auto) | B36: =IFERROR(COUNTIF(M129:M178,"Confirmed"),0) -> 0 | C36: # | D36: ⚡ Auto-count from Orders Detail table (Section 9)
A37: Orders — In Production (auto) | B37: =IFERROR(COUNTIF(M129:M178,"In Production"),0) -> 0 | C37: # | D37: ⚡ Auto-count from Orders Detail table (Section 9)
A38: Orders — Shipped (auto) | B38: =IFERROR(COUNTIF(M129:M178,"Shipped"),0) -> 0 | C38: # | D38: ⚡ Auto-count from Orders Detail table (Section 9)
A39: Orders — Delivered (auto) | B39: =IFERROR(COUNTIF(M129:M178,"Delivered"),0) -> 0 | C39: # | D39: ⚡ Auto-count from Orders Detail table (Section 9)
A40: Total Orders (auto) | B40: =IFERROR(SUM(B35:B39),0) -> 0 | C40: # | D40: Auto-calculated: sum of all pipeline stages
A41: Order Fulfillment Rate | C41: % | D41: Manual KPI: % of expected orders fulfilled to date
A43: ▌ SECTION 4 — SUPPLY CHAIN: INVENTORY
A44: Stock On Hand | C44: MT | D44: Physical stock in FAO warehouses
A45: Stock In Transit | C45: MT | D45: Stock en route to destination warehouses
A46: Total Stock (auto) | B46: =IFERROR(B44+B45,"") -> 0 | C46: MT | D46: Auto-calculated
A47: Warehouse Capacity (total) | C47: MT | D47: Total warehouse capacity available
A48: Capacity Utilization % (auto) | B48: =IFERROR((B44+B45)/B47,"") | C48: % | D48: Auto-calculated
A49: Warehouse Location 1 | C49: city | D49: Main hub
A50: Warehouse Location 2 | C50: city | D50: Secondary hub (if applicable)
A51: Warehouse Location 3 | C51: city
A52: Warehouse Location 4 | C52: city
A54: ▌ SECTION 5 — SUPPLY CHAIN: DELIVERIES & LAST MILE
A55: Planned Deliveries (total) | C55: # | D55: Total delivery events planned
A56: Dispatched | C56: # | D56: Delivery events dispatched from warehouse
A57: Received by Partners | C57: # | D57: Confirmed received by implementing partners
A58: Last Mile Completed | C58: # | D58: Completed to final beneficiaries
A59: Dispatch Rate % (auto) | B59: =IFERROR(B56/B55,"") | C59: % | D59: Auto-calculated
A60: Partner Receipt Rate % (auto) | B60: =IFERROR(B57/B55,"") | C60: % | D60: Auto-calculated
A61: Last Mile Rate % (auto) | B61: =IFERROR(B58/B55,"") | C61: % | D61: Auto-calculated
A62: Main Transport Mode | D62: e.g. Road, River, Air, Sea, Mixed
A63: Last Mile Partner 1
A64: Last Mile Partner 2
A65: Last Mile Partner 3
A66: Last Mile Partner 4
A68: ▌ SECTION 6 — SC PERFORMANCE KPIs
A69: On-Time Delivery Rate | C69: % | D69: % of deliveries on time vs. planned schedule
A70: Stockout Risk Level | D70: Select stockout risk assessment
A71: SC Overall Assessment | D71: Traffic-light assessment of overall SC health
A72: SC Comments / Notes | D72: Key issues, highlights, actions needed
A74: ▌ SECTION 7 — RISK REGISTER
A75: Risk # | B75: Risk Level | C75: Risk Description | D75: Mitigation Measure / Owner
A76: 1
A77: 2
A78: 3
A79: 4
A80: 5
A81: 6
A82: 7
A83: 8
A85: GSCMTF | FAO — CSLO | Confidential — For Internal Use Only
A86: 🔵 Blue text = Manual input | ⚫ Black text = Auto-calculated formula | ⚡ = Fed by detail table below | Yellow bg = Input cell | Blue-tint bg = Formula cell
A89: ▌ SECTION 8 — BUDGET DETAIL | Enter each budget line here → feeds Section 1 (Budget Spent & Committed)
A90: # | B90: Budget Category | C90: Description / Activity | D90: Vendor / Supplier / Partner | E90: Reference / Contract # | F90: Amount (USD) | G90: Date | H90: Payment Status | I90: Notes / Remarks
A91: 1
A92: 2
A93: 3
A94: 4
A95: 5
A96: 6
A97: 7
A98: 8
A99: 9
A100: 10
A101: 11
A102: 12
... A125: 35
A126: TOTALS | F126: =IFERROR(SUM(F91:F125),0) -> 0
A127: ▌ SECTION 9 — ORDERS DETAIL | Enter each order here → feeds Section 3 order pipeline counts
A128: # | B128: Order Ref / PO # | C128: Commodity / Item | D128: Unit | E128: Qty Ordered | F128: Qty Received | G128: Unit Cost (USD) | H128: Total Value (auto, USD) | I128: Supplier | J128: PO / Confirm. Date | K128: Expected Delivery | L128: Actual Delivery | M128: Status | N128: Notes
A129: 1 | H129: =IFERROR(E129*G129,"") -> 0
A130: 2 | H130: =IFERROR(E130*G130,"") -> 0
A131: 3 | H131: =IFERROR(E131*G131,"") -> 0
A132: 4 | H132: =IFERROR(E132*G132,"") -> 0
...

Sheet Myanmar
A1: GSCMTF | US-OCHA Global Project — Myanmar (MMR) | Region: South-East Asia
A2: FAO Supply Chain Orchestration Unit (CSLO) | Confidential — Internal Use Only
A3: Last Updated: | C3: Updated by:
A5: ▌ SECTION 1 — PROGRAMMATIC INFORMATION
A6: Project Status | D6: Select current overall project status
A7: Total Budget (USD) | C7: USD | D7: Total budget allocated to this country
A8: Budget Spent to Date (auto) | B8: =IFERROR(SUMIF(H91:H125,"Spent",F91:F125),0) -> 0 | C8: USD | D8: ⚡ Auto-sum from Budget Detail table (Section 8)
A9: Budget Committed (auto) | B9: =IFERROR(SUMIF(H91:H125,"Committed",F91:F125),0) -> 0 | C9: USD | D9: ⚡ Auto-sum from Budget Detail table (Section 8)
A10: Budget Available (auto) | B10: =IFERROR(B7-B8-B9,"") -> 0 | C10: USD | D10: Auto-calculated: Total − Spent − Committed
A11: Budget Utilized % (auto) | B11: =IFERROR(B8/B7,"") | C11: % | D11: Auto-calculated
A12: Target Beneficiaries | C12: # | D12: Total number of targeted beneficiaries
A13: Beneficiaries Reached | C13: # | D13: Cumulative beneficiaries reached to date
A14: Beneficiary Coverage % (auto) | B14: =IFERROR(B13/B12,"") | C14: % | D14: Auto-calculated
A15: Total Distribution Months | C15: months | D15: Total planned distribution months
A16: Distributions Completed | C16: months | D16: Number of distribution months completed
A17: Distribution Progress % (auto) | B17: =IFERROR(B16/B15,"") | C17: % | D17: Auto-calculated
A18: Next Distribution Date | C18: date | D18: Planned date of next distribution
A19: Project Start Date | C19: date | D19: Official project start date
A20: Project End Date | C20: date | D20: Official project end date
A21: Project Officer (FAO) | D21: Name of responsible FAO Project Officer
A22: FAO Country Office | D22: FAO country office responsible for implementation
A24: ▌ SECTION 2 — COMMODITIES / ITEMS DISTRIBUTED
A25: Commodity / Item 1 | C25: name | D25: e.g. Rice, Lentils, Cooking Oil, CSB+, Soap, NFIs…
A26: Commodity / Item 2 | C26: name | D26: e.g. Rice, Lentils, Cooking Oil, CSB+, Soap, NFIs…
A27: Commodity / Item 3 | C27: name | D27: e.g. Rice, Lentils, Cooking Oil, CSB+, Soap, NFIs…
A28: Commodity / Item 4 | C28: name | D28: e.g. Rice, Lentils, Cooking Oil, CSB+, Soap, NFIs…
A29: Commodity / Item 5 | C29: name | D29: e.g. Rice, Lentils, Cooking Oil, CSB+, Soap, NFIs…
A30: Commodity / Item 6 | C30: name | D30: e.g. Rice, Lentils, Cooking Oil, CSB+, Soap, NFIs…
A31: Commodity / Item 7 | C31: name | D31: e.g. Rice, Lentils, Cooking Oil, CSB+, Soap, NFIs…
A32: Commodity / Item 8 | C32: name | D32: e.g. Rice, Lentils, Cooking Oil, CSB+, Soap, NFIs…
A34: ▌ SECTION 3 — SUPPLY CHAIN: ORDERS (auto-counted from Section 9 detail table)
A35: Orders — Pending (auto) | B35: =IFERROR(COUNTIF(M129:M178,"Pending"),0) -> 0 | C35: # | D35: ⚡ Auto-count from Orders Detail table (Section 9)
A36: Orders — Confirmed (auto) | B36: =IFERROR(COUNTIF(M129:M178,"Confirmed"),0) -> 0 | C36: # | D36: ⚡ Auto-count from Orders Detail table (Section 9)
A37: Orders — In Production (auto) | B37: =IFERROR(COUNTIF(M129:M178,"In Production"),0) -> 0 | C37: # | D37: ⚡ Auto-count from Orders Detail table (Section 9)
A38: Orders — Shipped (auto) | B38: =IFERROR(COUNTIF(M129:M178,"Shipped"),0) -> 0 | C38: # | D38: ⚡ Auto-count from Orders Detail table (Section 9)
A39: Orders — Delivered (auto) | B39: =IFERROR(COUNTIF(M129:M178,"Delivered"),0) -> 0 | C39: # | D39: ⚡ Auto-count from Orders Detail table (Section 9)
A40: Total Orders (auto) | B40: =IFERROR(SUM(B35:B39),0) -> 0 | C40: # | D40: Auto-calculated: sum of all pipeline stages
A41: Order Fulfillment Rate | C41: % | D41: Manual KPI: % of expected orders fulfilled to date
A43: ▌ SECTION 4 — SUPPLY CHAIN: INVENTORY
A44: Stock On Hand | C44: MT | D44: Physical stock in FAO warehouses
A45: Stock In Transit | C45: MT | D45: Stock en route to destination warehouses
A46: Total Stock (auto) | B46: =IFERROR(B44+B45,"") -> 0 | C46: MT | D46: Auto-calculated
A47: Warehouse Capacity (total) | C47: MT | D47: Total warehouse capacity available
A48: Capacity Utilization % (auto) | B48: =IFERROR((B44+B45)/B47,"") | C48: % | D48: Auto-calculated
A49: Warehouse Location 1 | C49: city | D49: Main hub
A50: Warehouse Location 2 | C50: city | D50: Secondary hub (if applicable)
A51: Warehouse Location 3 | C51: city
A52: Warehouse Location 4 | C52: city
A54: ▌ SECTION 5 — SUPPLY CHAIN: DELIVERIES & LAST MILE
A55: Planned Deliveries (total) | C55: # | D55: Total delivery events planned
A56: Dispatched | C56: # | D56: Delivery events dispatched from warehouse
A57: Received by Partners | C57: # | D57: Confirmed received by implementing partners
A58: Last Mile Completed | C58: # | D58: Completed to final beneficiaries
A59: Dispatch Rate % (auto) | B59: =IFERROR(B56/B55,"") | C59: % | D59: Auto-calculated
A60: Partner Receipt Rate % (auto) | B60: =IFERROR(B57/B55,"") | C60: % | D60: Auto-calculated
A61: Last Mile Rate % (auto) | B61: =IFERROR(B58/B55,"") | C61: % | D61: Auto-calculated
A62: Main Transport Mode | D62: e.g. Road, River, Air, Sea, Mixed
A63: Last Mile Partner 1
A64: Last Mile Partner 2
A65: Last Mile Partner 3
A66: Last Mile Partner 4
A68: ▌ SECTION 6 — SC PERFORMANCE KPIs
A69: On-Time Delivery Rate | C69: % | D69: % of deliveries on time vs. planned schedule
A70: Stockout Risk Level | D70: Select stockout risk assessment
A71: SC Overall Assessment | D71: Traffic-light assessment of overall SC health
A72: SC Comments / Notes | D72: Key issues, highlights, actions needed
A74: ▌ SECTION 7 — RISK REGISTER
A75: Risk # | B75: Risk Level | C75: Risk Description | D75: Mitigation Measure / Owner
A76: 1
A77: 2
A78: 3
A79: 4
A80: 5
A81: 6
A82: 7
A83: 8
A85: GSCMTF | FAO — CSLO | Confidential — For Internal Use Only
A86: 🔵 Blue text = Manual input | ⚫ Black text = Auto-calculated formula | ⚡ = Fed by detail table below | Yellow bg = Input cell | Blue-tint bg = Formula cell
A89: ▌ SECTION 8 — BUDGET DETAIL | Enter each budget line here → feeds Section 1 (Budget Spent & Committed)
A90: # | B90: Budget Category | C90: Description / Activity | D90: Vendor / Supplier / Partner | E90: Reference / Contract # | F90: Amount (USD) | G90: Date | H90: Payment Status | I90: Notes / Remarks
A91: 1
A92: 2
A93: 3
A94: 4
A95: 5
A96: 6
A97: 7
A98: 8
A99: 9
A100: 10
A101: 11
A102: 12
... A125: 35
A126: TOTALS | F126: =IFERROR(SUM(F91:F125),0) -> 0
A127: ▌ SECTION 9 — ORDERS DETAIL | Enter each order here → feeds Section 3 order pipeline counts
A128: # | B128: Order Ref / PO # | C128: Commodity / Item | D128: Unit | E128: Qty Ordered | F128: Qty Received | G128: Unit Cost (USD) | H128: Total Value (auto, USD) | I128: Supplier | J128: PO / Confirm. Date | K128: Expected Delivery | L128: Actual Delivery | M128: Status | N128: Notes
A129: 1 | H129: =IFERROR(E129*G129,"") -> 0
A130: 2 | H130: =IFERROR(E130*G130,"") -> 0
A131: 3 | H131: =IFERROR(E131*G131,"") -> 0
A132: 4 | H132: =IFERROR(E132*G132,"") -> 0
...

Sheet Syria
A1: GSCMTF | US-OCHA Global Project — Syria (SYR) | Region: Middle East
A2: FAO Supply Chain Orchestration Unit (CSLO) | Confidential — Internal Use Only
A3: Last Updated: | C3: Updated by:
A5: ▌ SECTION 1 — PROGRAMMATIC INFORMATION
A6: Project Status | D6: Select current overall project status
A7: Total Budget (USD) | C7: USD | D7: Total budget allocated to this country
A8: Budget Spent to Date (auto) | B8: =IFERROR(SUMIF(H91:H125,"Spent",F91:F125),0) -> 0 | C8: USD | D8: ⚡ Auto-sum from Budget Detail table (Section 8)
A9: Budget Committed (auto) | B9: =IFERROR(SUMIF(H91:H125,"Committed",F91:F125),0) -> 0 | C9: USD | D9: ⚡ Auto-sum from Budget Detail table (Section 8)
A10: Budget Available (auto) | B10: =IFERROR(B7-B8-B9,"") -> 0 | C10: USD | D10: Auto-calculated: Total − Spent − Committed
A11: Budget Utilized % (auto) | B11: =IFERROR(B8/B7,"") | C11: % | D11: Auto-calculated
A12: Target Beneficiaries | C12: # | D12: Total number of targeted beneficiaries
A13: Beneficiaries Reached | C13: # | D13: Cumulative beneficiaries reached to date
A14: Beneficiary Coverage % (auto) | B14: =IFERROR(B13/B12,"") | C14: % | D14: Auto-calculated
A15: Total Distribution Months | C15: months | D15: Total planned distribution months
A16: Distributions Completed | C16: months | D16: Number of distribution months completed
A17: Distribution Progress % (auto) | B17: =IFERROR(B16/B15,"") | C17: % | D17: Auto-calculated
A18: Next Distribution Date | C18: date | D18: Planned date of next distribution
A19: Project Start Date | C19: date | D19: Official project start date
A20: Project End Date | C20: date | D20: Official project end date
A21: Project Officer (FAO) | D21: Name of responsible FAO Project Officer
A22: FAO Country Office | D22: FAO country office responsible for implementation
A24: ▌ SECTION 2 — COMMODITIES / ITEMS DISTRIBUTED
A25: Commodity / Item 1 | C25: name | D25: e.g. Rice, Lentils, Cooking Oil, CSB+, Soap, NFIs…
A26: Commodity / Item 2 | C26: name | D26: e.g. Rice, Lentils, Cooking Oil, CSB+, Soap, NFIs…
A27: Commodity / Item 3 | C27: name | D27: e.g. Rice, Lentils, Cooking Oil, CSB+, Soap, NFIs…
A28: Commodity / Item 4 | C28: name | D28: e.g. Rice, Lentils, Cooking Oil, CSB+, Soap, NFIs…
A29: Commodity / Item 5 | C29: name | D29: e.g. Rice, Lentils, Cooking Oil, CSB+, Soap, NFIs…
A30: Commodity / Item 6 | C30: name | D30: e.g. Rice, Lentils, Cooking Oil, CSB+, Soap, NFIs…
A31: Commodity / Item 7 | C31: name | D31: e.g. Rice, Lentils, Cooking Oil, CSB+, Soap, NFIs…
A32: Commodity / Item 8 | C32: name | D32: e.g. Rice, Lentils, Cooking Oil, CSB+, Soap, NFIs…
A34: ▌ SECTION 3 — SUPPLY CHAIN: ORDERS (auto-counted from Section 9 detail table)
A35: Orders — Pending (auto) | B35: =IFERROR(COUNTIF(M129:M178,"Pending"),0) -> 0 | C35: # | D35: ⚡ Auto-count from Orders Detail table (Section 9)
A36: Orders — Confirmed (auto) | B36: =IFERROR(COUNTIF(M129:M178,"Confirmed"),0) -> 0 | C36: # | D36: ⚡ Auto-count from Orders Detail table (Section 9)
A37: Orders — In Production (auto) | B37: =IFERROR(COUNTIF(M129:M178,"In Production"),0) -> 0 | C37: # | D37: ⚡ Auto-count from Orders Detail table (Section 9)
A38: Orders — Shipped (auto) | B38: =IFERROR(COUNTIF(M129:M178,"Shipped"),0) -> 0 | C38: # | D38: ⚡ Auto-count from Orders Detail table (Section 9)
A39: Orders — Delivered (auto) | B39: =IFERROR(COUNTIF(M129:M178,"Delivered"),0) -> 0 | C39: # | D39: ⚡ Auto-count from Orders Detail table (Section 9)
A40: Total Orders (auto) | B40: =IFERROR(SUM(B35:B39),0) -> 0 | C40: # | D40: Auto-calculated: sum of all pipeline stages
A41: Order Fulfillment Rate | C41: % | D41: Manual KPI: % of expected orders fulfilled to date
A43: ▌ SECTION 4 — SUPPLY CHAIN: INVENTORY
A44: Stock On Hand | C44: MT | D44: Physical stock in FAO warehouses
A45: Stock In Transit | C45: MT | D45: Stock en route to destination warehouses
A46: Total Stock (auto) | B46: =IFERROR(B44+B45,"") -> 0 | C46: MT | D46: Auto-calculated
A47: Warehouse Capacity (total) | C47: MT | D47: Total warehouse capacity available
A48: Capacity Utilization % (auto) | B48: =IFERROR((B44+B45)/B47,"") | C48: % | D48: Auto-calculated
A49: Warehouse Location 1 | C49: city | D49: Main hub
A50: Warehouse Location 2 | C50: city | D50: Secondary hub (if applicable)
A51: Warehouse Location 3 | C51: city
A52: Warehouse Location 4 | C52: city
A54: ▌ SECTION 5 — SUPPLY CHAIN: DELIVERIES & LAST MILE
A55: Planned Deliveries (total) | C55: # | D55: Total delivery events planned
A56: Dispatched | C56: # | D56: Delivery events dispatched from warehouse
A57: Received by Partners | C57: # | D57: Confirmed received by implementing partners
A58: Last Mile Completed | C58: # | D58: Completed to final beneficiaries
A59: Dispatch Rate % (auto) | B59: =IFERROR(B56/B55,"") | C59: % | D59: Auto-calculated
A60: Partner Receipt Rate % (auto) | B60: =IFERROR(B57/B55,"") | C60: % | D60: Auto-calculated
A61: Last Mile Rate % (auto) | B61: =IFERROR(B58/B55,"") | C61: % | D61: Auto-calculated
A62: Main Transport Mode | D62: e.g. Road, River, Air, Sea, Mixed
A63: Last Mile Partner 1
A64: Last Mile Partner 2
A65: Last Mile Partner 3
A66: Last Mile Partner 4
A68: ▌ SECTION 6 — SC PERFORMANCE KPIs
A69: On-Time Delivery Rate | C69: % | D69: % of deliveries on time vs. planned schedule
A70: Stockout Risk Level | D70: Select stockout risk assessment
A71: SC Overall Assessment | D71: Traffic-light assessment of overall SC health
A72: SC Comments / Notes | D72: Key issues, highlights, actions needed
A74: ▌ SECTION 7 — RISK REGISTER
A75: Risk # | B75: Risk Level | C75: Risk Description | D75: Mitigation Measure / Owner
A76: 1
A77: 2
A78: 3
A79: 4
A80: 5
A81: 6
A82: 7
A83: 8
A85: GSCMTF | FAO — CSLO | Confidential — For Internal Use Only
A86: 🔵 Blue text = Manual input | ⚫ Black text = Auto-calculated formula | ⚡ = Fed by detail table below | Yellow bg = Input cell | Blue-tint bg = Formula cell
A89: ▌ SECTION 8 — BUDGET DETAIL | Enter each budget line here → feeds Section 1 (Budget Spent & Committed)
A90: # | B90: Budget Category | C90: Description / Activity | D90: Vendor / Supplier / Partner | E90: Reference / Contract # | F90: Amount (USD) | G90: Date | H90: Payment Status | I90: Notes / Remarks
A91: 1
A92: 2
A93: 3
A94: 4
A95: 5
A96: 6
A97: 7
A98: 8
A99: 9
A100: 10
A101: 11
A102: 12
... A125: 35
A126: TOTALS | F126: =IFERROR(SUM(F91:F125),0) -> 0
A127: ▌ SECTION 9 — ORDERS DETAIL | Enter each order here → feeds Section 3 order pipeline counts
A128: # | B128: Order Ref / PO # | C128: Commodity / Item | D128: Unit | E128: Qty Ordered | F128: Qty Received | G128: Unit Cost (USD) | H128: Total Value (auto, USD) | I128: Supplier | J128: PO / Confirm. Date | K128: Expected Delivery | L128: Actual Delivery | M128: Status | N128: Notes
A129: 1 | H129: =IFERROR(E129*G129,"") -> 0
A130: 2 | H130: =IFERROR(E130*G130,"") -> 0
A131: 3 | H131: =IFERROR(E131*G131,"") -> 0
A132: 4 | H132: =IFERROR(E132*G132,"") -> 0
...
